{
  "H": {
    "appearance": "colorless gas",
    "mass": 1.008,
    "block": "s",
    "boil": 20.271,
    "density": 0.08988,
    "discoverer": "Henry Cavendish",
    "electron_affinity": 72.769,
    "electron_configuration": "1s1",
    "electronegativity": 2.2,
    "ionization_energies": [
      1312
    ],
    "melt": 13.99,
    "molar_heat": 28.836,
    "namer": "Antoine Lavoisier",
    "number": 1,
    "period": 1,
    "phase": "Gas",
    "shells": [
      1
    ],
    "group": "Diatomic Non-Metal",
    "name": "Hydrogen",
    "family": 1
  },
  "He": {
    "appearance": "colorless gas, exhibiting a red-orange glow when placed in a high-voltage electric field",
    "mass": 4.0026022,
    "block": "s",
    "boil": 4.222,
    "density": 0.1786,
    "discoverer": "Pierre Janssen",
    "electron_affinity": -48,
    "electron_configuration": "1s2",
    "electronegativity": null,
    "ionization_energies": [
      2372.3,
      5250.5
    ],
    "melt": 0.95,
    "molar_heat": null,
    "namer": null,
    "number": 2,
    "period": 1,
    "phase": "Gas",
    "shells": [
      2
    ],
    "group": "Noble Gas",
    "name": "Helium",
    "family": 18
  },
  "Li": {
    "appearance": "silvery-white",
    "mass": 6.94,
    "block": "s",
    "boil": 1603,
    "density": 0.534,
    "discoverer": "Johan August Arfwedson",
    "electron_affinity": 59.6326,
    "electron_configuration": "[He] 2s1",
    "electronegativity": 0.98,
    "ionization_energies": [
      520.2,
      7298.1,
      11815
    ],
    "melt": 453.65,
    "molar_heat": 24.86,
    "namer": null,
    "number": 3,
    "period": 2,
    "phase": "Solid",
    "shells": [
      2,
      1
    ],
    "group": "Alkali Metal",
    "name": "Lithium",
    "family": 1
  },
  "Be": {
    "appearance": "white-gray metallic",
    "mass": 9.01218315,
    "block": "s",
    "boil": 2742,
    "density": 1.85,
    "discoverer": "Louis Nicolas Vauquelin",
    "electron_affinity": -48,
    "electron_configuration": "[He] 2s2",
    "electronegativity": 1.57,
    "ionization_energies": [
      899.5,
      1757.1,
      14848.7,
      21006.6
    ],
    "melt": 1560,
    "molar_heat": 16.443,
    "namer": null,
    "number": 4,
    "period": 2,
    "phase": "Solid",
    "shells": [
      2,
      2
    ],
    "group": "Alkaline Earth Metal",
    "name": "Beryllium",
    "family": 2
  },
  "B": {
    "appearance": "black-brown",
    "mass": 10.81,
    "block": "p",
    "boil": 4200,
    "density": 2.08,
    "discoverer": "Joseph Louis Gay-Lussac",
    "electron_affinity": 26.989,
    "electron_configuration": "[He] 2s2 2p1",
    "electronegativity": 2.04,
    "ionization_energies": [
      800.6,
      2427.1,
      3659.7,
      25025.8,
      32826.7
    ],
    "melt": 2349,
    "molar_heat": 11.087,
    "namer": null,
    "number": 5,
    "period": 2,
    "phase": "Solid",
    "shells": [
      2,
      3
    ],
    "group": "Metalloid",
    "name": "Boron",
    "family": 13
  },
  "C": {
    "appearance": null,
    "mass": 12.011,
    "block": "p",
    "boil": null,
    "density": 1.821,
    "discoverer": "Ancient Egypt",
    "electron_affinity": 121.7763,
    "electron_configuration": "[He] 2s2 2p2",
    "electronegativity": 2.55,
    "ionization_energies": [
      1086.5,
      2352.6,
      4620.5,
      6222.7,
      37831,
      47277
    ],
    "melt": null,
    "molar_heat": 8.517,
    "namer": null,
    "number": 6,
    "period": 2,
    "phase": "Solid",
    "shells": [
      2,
      4
    ],
    "group": "Polyatomic Non-Metal",
    "name": "Carbon",
    "family": 14
  },
  "N": {
    "appearance": "colorless gas, liquid or solid",
    "mass": 14.007,
    "block": "p",
    "boil": 77.355,
    "density": 1.251,
    "discoverer": "Daniel Rutherford",
    "electron_affinity": -6.8,
    "electron_configuration": "[He] 2s2 2p3",
    "electronegativity": 3.04,
    "ionization_energies": [
      1402.3,
      2856,
      4578.1,
      7475,
      9444.9,
      53266.6,
      64360
    ],
    "melt": 63.15,
    "molar_heat": null,
    "namer": "Jean-Antoine Chaptal",
    "number": 7,
    "period": 2,
    "phase": "Gas",
    "shells": [
      2,
      5
    ],
    "group": "Diatomic Non-Metal",
    "name": "Nitrogen",
    "family": 15
  },
  "O": {
    "appearance": null,
    "mass": 15.999,
    "block": "p",
    "boil": 90.188,
    "density": 1.429,
    "discoverer": "Carl Wilhelm Scheele",
    "electron_affinity": 140.976,
    "electron_configuration": "[He] 2s2 2p4",
    "electronegativity": 3.44,
    "ionization_energies": [
      1313.9,
      3388.3,
      5300.5,
      7469.2,
      10989.5,
      13326.5,
      71330,
      84078
    ],
    "melt": 54.36,
    "molar_heat": null,
    "namer": "Antoine Lavoisier",
    "number": 8,
    "period": 2,
    "phase": "Gas",
    "shells": [
      2,
      6
    ],
    "group": "Diatomic Non-Metal",
    "name": "Oxygen",
    "family": 16
  },
  "F": {
    "appearance": null,
    "mass": 18.9984031636,
    "block": "p",
    "boil": 85.03,
    "density": 1.696,
    "discoverer": "André-Marie Ampère",
    "electron_affinity": 328.1649,
    "electron_configuration": "[He] 2s2 2p5",
    "electronegativity": 3.98,
    "ionization_energies": [
      1681,
      3374.2,
      6050.4,
      8407.7,
      11022.7,
      15164.1,
      17868,
      92038.1,
      106434.3
    ],
    "melt": 53.48,
    "molar_heat": null,
    "namer": "Humphry Davy",
    "number": 9,
    "period": 2,
    "phase": "Gas",
    "shells": [
      2,
      7
    ],
    "group": "Diatomic Non-Metal",
    "name": "Fluorine",
    "family": 17
  },
  "Ne": {
    "appearance": "colorless gas exhibiting an orange-red glow when placed in a high voltage electric field",
    "mass": 20.17976,
    "block": "p",
    "boil": 27.104,
    "density": 0.9002,
    "discoverer": "Morris Travers",
    "electron_affinity": -116,
    "electron_configuration": "[He] 2s2 2p6",
    "electronegativity": null,
    "ionization_energies": [
      2080.7,
      3952.3,
      6122,
      9371,
      12177,
      15238,
      19999,
      23069.5,
      115379.5,
      131432
    ],
    "melt": 24.56,
    "molar_heat": null,
    "namer": null,
    "number": 10,
    "period": 2,
    "phase": "Gas",
    "shells": [
      2,
      8
    ],
    "group": "Noble Gas",
    "name": "Neon",
    "family": 18
  },
  "Na": {
    "appearance": "silvery white metallic",
    "mass": 22.989769282,
    "block": "s",
    "boil": 1156.09,
    "density": 0.968,
    "discoverer": "Humphry Davy",
    "electron_affinity": 52.867,
    "electron_configuration": "[Ne] 3s1",
    "electronegativity": 0.93,
    "ionization_energies": [
      495.8,
      4562,
      6910.3,
      9543,
      13354,
      16613,
      20117,
      25496,
      28932,
      141362,
      159076
    ],
    "melt": 370.944,
    "molar_heat": 28.23,
    "namer": null,
    "number": 11,
    "period": 3,
    "phase": "Solid",
    "shells": [
      2,
      8,
      1
    ],
    "group": "Alkali Metal",
    "name": "Sodium",
    "family": 1
  },
  "Mg": {
    "appearance": "shiny grey solid",
    "mass": 24.305,
    "block": "s",
    "boil": 1363,
    "density": 1.738,
    "discoverer": "Joseph Black",
    "electron_affinity": -40,
    "electron_configuration": "[Ne] 3s2",
    "electronegativity": 1.31,
    "ionization_energies": [
      737.7,
      1450.7,
      7732.7,
      10542.5,
      13630,
      18020,
      21711,
      25661,
      31653,
      35458,
      169988,
      189368
    ],
    "melt": 923,
    "molar_heat": 24.869,
    "namer": null,
    "number": 12,
    "period": 3,
    "phase": "Solid",
    "shells": [
      2,
      8,
      2
    ],
    "group": "Alkaline Earth Metal",
    "name": "Magnesium",
    "family": 2
  },
  "Al": {
    "appearance": "silvery gray metallic",
    "mass": 26.98153857,
    "block": "p",
    "boil": 2743,
    "density": 2.7,
    "discoverer": null,
    "electron_affinity": 41.762,
    "electron_configuration": "[Ne] 3s2 3p1",
    "electronegativity": 1.61,
    "ionization_energies": [
      577.5,
      1816.7,
      2744.8,
      11577,
      14842,
      18379,
      23326,
      27465,
      31853,
      38473,
      42647,
      201266,
      222316
    ],
    "melt": 933.47,
    "molar_heat": 24.2,
    "namer": "Humphry Davy",
    "number": 13,
    "period": 3,
    "phase": "Solid",
    "shells": [
      2,
      8,
      3
    ],
    "group": "Post-Transition Metal",
    "name": "Aluminium",
    "family": 13
  },
  "Si": {
    "appearance": "crystalline, reflective with bluish-tinged faces",
    "mass": 28.085,
    "block": "p",
    "boil": 3538,
    "density": 2.329,
    "discoverer": "Jöns Jacob Berzelius",
    "electron_affinity": 134.0684,
    "electron_configuration": "[Ne] 3s2 3p2",
    "electronegativity": 1.9,
    "ionization_energies": [
      786.5,
      1577.1,
      3231.6,
      4355.5,
      16091,
      19805,
      23780,
      29287,
      33878,
      38726,
      45962,
      50502,
      235196,
      257923
    ],
    "melt": 1687,
    "molar_heat": 19.789,
    "namer": "Thomas Thomson (chemist)",
    "number": 14,
    "period": 3,
    "phase": "Solid",
    "shells": [
      2,
      8,
      4
    ],
    "group": "Metalloid",
    "name": "Silicon",
    "family": 14
  },
  "P": {
    "appearance": "colourless, waxy white, yellow, scarlet, red, violet, black",
    "mass": 30.9737619985,
    "block": "p",
    "boil": null,
    "density": 1.823,
    "discoverer": "Hennig Brand",
    "electron_affinity": 72.037,
    "electron_configuration": "[Ne] 3s2 3p3",
    "electronegativity": 2.19,
    "ionization_energies": [
      1011.8,
      1907,
      2914.1,
      4963.6,
      6273.9,
      21267,
      25431,
      29872,
      35905,
      40950,
      46261,
      54110,
      59024,
      271791,
      296195
    ],
    "melt": null,
    "molar_heat": 23.824,
    "namer": null,
    "number": 15,
    "period": 3,
    "phase": "Solid",
    "shells": [
      2,
      8,
      5
    ],
    "group": "Polyatomic Non-Metal",
    "name": "Phosphorus",
    "family": 15
  },
  "S": {
    "appearance": "lemon yellow sintered microcrystals",
    "mass": 32.06,
    "block": "p",
    "boil": 717.8,
    "density": 2.07,
    "discoverer": "Ancient china",
    "electron_affinity": 200.4101,
    "electron_configuration": "[Ne] 3s2 3p4",
    "electronegativity": 2.58,
    "ionization_energies": [
      999.6,
      2252,
      3357,
      4556,
      7004.3,
      8495.8,
      27107,
      31719,
      36621,
      43177,
      48710,
      54460,
      62930,
      68216,
      311048,
      337138
    ],
    "melt": 388.36,
    "molar_heat": 22.75,
    "namer": null,
    "number": 16,
    "period": 3,
    "phase": "Solid",
    "shells": [
      2,
      8,
      6
    ],
    "group": "Polyatomic Non-Metal",
    "name": "Sulfur",
    "family": 16
  },
  "Cl": {
    "appearance": "pale yellow-green gas",
    "mass": 35.45,
    "block": "p",
    "boil": 239.11,
    "density": 3.2,
    "discoverer": "Carl Wilhelm Scheele",
    "electron_affinity": 348.575,
    "electron_configuration": "[Ne] 3s2 3p5",
    "electronegativity": 3.16,
    "ionization_energies": [
      1251.2,
      2298,
      3822,
      5158.6,
      6542,
      9362,
      11018,
      33604,
      38600,
      43961,
      51068,
      57119,
      63363,
      72341,
      78095,
      352994,
      380760
    ],
    "melt": 171.6,
    "molar_heat": null,
    "namer": null,
    "number": 17,
    "period": 3,
    "phase": "Gas",
    "shells": [
      2,
      8,
      7
    ],
    "group": "Diatomic Non-Metal",
    "name": "Chlorine",
    "family": 17
  },
  "Ar": {
    "appearance": "colorless gas exhibiting a lilac/violet glow when placed in a high voltage electric field",
    "mass": 39.9481,
    "block": "p",
    "boil": 87.302,
    "density": 1.784,
    "discoverer": "Lord Rayleigh",
    "electron_affinity": -96,
    "electron_configuration": "[Ne] 3s2 3p6",
    "electronegativity": null,
    "ionization_energies": [
      1520.6,
      2665.8,
      3931,
      5771,
      7238,
      8781,
      11995,
      13842,
      40760,
      46186,
      52002,
      59653,
      66199,
      72918,
      82473,
      88576,
      397605,
      427066
    ],
    "melt": 83.81,
    "molar_heat": null,
    "namer": null,
    "number": 18,
    "period": 3,
    "phase": "Gas",
    "shells": [
      2,
      8,
      8
    ],
    "group": "Noble Gas",
    "name": "Argon",
    "family": 18
  },
  "K": {
    "appearance": "silvery gray",
    "mass": 39.09831,
    "block": "s",
    "boil": 1032,
    "density": 0.862,
    "discoverer": "Humphry Davy",
    "electron_affinity": 48.383,
    "electron_configuration": "[Ar] 4s1",
    "electronegativity": 0.82,
    "ionization_energies": [
      418.8,
      3052,
      4420,
      5877,
      7975,
      9590,
      11343,
      14944,
      16963.7,
      48610,
      54490,
      60730,
      68950,
      75900,
      83080,
      93400,
      99710,
      444880,
      476063
    ],
    "melt": 336.7,
    "molar_heat": 29.6,
    "namer": null,
    "number": 19,
    "period": 4,
    "phase": "Solid",
    "shells": [
      2,
      8,
      8,
      1
    ],
    "group": "Alkali Metal",
    "name": "Potassium",
    "family": 1
  },
  "Ca": {
    "appearance": null,
    "mass": 40.0784,
    "block": "s",
    "boil": 1757,
    "density": 1.55,
    "discoverer": "Humphry Davy",
    "electron_affinity": 2.37,
    "electron_configuration": "[Ar] 4s2",
    "electronegativity": 1,
    "ionization_energies": [
      589.8,
      1145.4,
      4912.4,
      6491,
      8153,
      10496,
      12270,
      14206,
      18191,
      20385,
      57110,
      63410,
      70110,
      78890,
      86310,
      94000,
      104900,
      111711,
      494850,
      527762
    ],
    "melt": 1115,
    "molar_heat": 25.929,
    "namer": null,
    "number": 20,
    "period": 4,
    "phase": "Solid",
    "shells": [
      2,
      8,
      8,
      2
    ],
    "group": "Alkaline Earth Metal",
    "name": "Calcium",
    "family": 2
  },
  "Sc": {
    "appearance": "silvery white",
    "mass": 44.9559085,
    "block": "d",
    "boil": 3109,
    "density": 2.985,
    "discoverer": "Lars Fredrik Nilson",
    "electron_affinity": 18,
    "electron_configuration": "[Ar] 3d1 4s2",
    "electronegativity": 1.36,
    "ionization_energies": [
      633.1,
      1235,
      2388.6,
      7090.6,
      8843,
      10679,
      13310,
      15250,
      17370,
      21726,
      24102,
      66320,
      73010,
      80160,
      89490,
      97400,
      105600,
      117000,
      124270,
      547530,
      582163
    ],
    "melt": 1814,
    "molar_heat": 25.52,
    "namer": null,
    "number": 21,
    "period": 4,
    "phase": "Solid",
    "shells": [
      2,
      8,
      9,
      2
    ],
    "group": "Transition Metal",
    "name": "Scandium",
    "family": 3
  },
  "Ti": {
    "appearance": "silvery grey-white metallic",
    "mass": 47.8671,
    "block": "d",
    "boil": 3560,
    "density": 4.506,
    "discoverer": "William Gregor",
    "electron_affinity": 7.289,
    "electron_configuration": "[Ar] 3d2 4s2",
    "electronegativity": 1.54,
    "ionization_energies": [
      658.8,
      1309.8,
      2652.5,
      4174.6,
      9581,
      11533,
      13590,
      16440,
      18530,
      20833,
      25575,
      28125,
      76015,
      83280,
      90880,
      100700,
      109100,
      117800,
      129900,
      137530,
      602930,
      639294
    ],
    "melt": 1941,
    "molar_heat": 25.06,
    "namer": "Martin Heinrich Klaproth",
    "number": 22,
    "period": 4,
    "phase": "Solid",
    "shells": [
      2,
      8,
      10,
      2
    ],
    "group": "Transition Metal",
    "name": "Titanium",
    "family": 4
  },
  "V": {
    "appearance": "blue-silver-grey metal",
    "mass": 50.94151,
    "block": "d",
    "boil": 3680,
    "density": 6,
    "discoverer": "Andrés Manuel del Río",
    "electron_affinity": 50.911,
    "electron_configuration": "[Ar] 3d3 4s2",
    "electronegativity": 1.63,
    "ionization_energies": [
      650.9,
      1414,
      2830,
      4507,
      6298.7,
      12363,
      14530,
      16730,
      19860,
      22240,
      24670,
      29730,
      32446,
      86450,
      94170,
      102300,
      112700,
      121600,
      130700,
      143400,
      151440,
      661050,
      699144
    ],
    "melt": 2183,
    "molar_heat": 24.89,
    "namer": "Isotopes of vanadium",
    "number": 23,
    "period": 4,
    "phase": "Solid",
    "shells": [
      2,
      8,
      11,
      2
    ],
    "group": "Transition Metal",
    "name": "Vanadium",
    "family": 5
  },
  "Cr": {
    "appearance": "silvery metallic",
    "mass": 51.99616,
    "block": "d",
    "boil": 2944,
    "density": 7.19,
    "discoverer": "Louis Nicolas Vauquelin",
    "electron_affinity": 65.21,
    "electron_configuration": "[Ar] 3d5 4s1",
    "electronegativity": 1.66,
    "ionization_energies": [
      652.9,
      1590.6,
      2987,
      4743,
      6702,
      8744.9,
      15455,
      17820,
      20190,
      23580,
      26130,
      28750,
      34230,
      37066,
      97510,
      105800,
      114300,
      125300,
      134700,
      144300,
      157700,
      166090,
      721870,
      761733
    ],
    "melt": 2180,
    "molar_heat": 23.35,
    "namer": null,
    "number": 24,
    "period": 4,
    "phase": "Solid",
    "shells": [
      2,
      8,
      13,
      1
    ],
    "group": "Transition Metal",
    "name": "Chromium",
    "family": 6
  },
  "Mn": {
    "appearance": "silvery metallic",
    "mass": 54.9380443,
    "block": "d",
    "boil": 2334,
    "density": 7.21,
    "discoverer": "Torbern Olof Bergman",
    "electron_affinity": -50,
    "electron_configuration": "[Ar] 3d5 4s2",
    "electronegativity": 1.55,
    "ionization_energies": [
      717.3,
      1509,
      3248,
      4940,
      6990,
      9220,
      11500,
      18770,
      21400,
      23960,
      27590,
      30330,
      33150,
      38880,
      41987,
      109480,
      118100,
      127100,
      138600,
      148500,
      158600,
      172500,
      181380,
      785450,
      827067
    ],
    "melt": 1519,
    "molar_heat": 26.32,
    "namer": null,
    "number": 25,
    "period": 4,
    "phase": "Solid",
    "shells": [
      2,
      8,
      13,
      2
    ],
    "group": "Transition Metal",
    "name": "Manganese",
    "family": 7
  },
  "Fe": {
    "appearance": "lustrous metallic with a grayish tinge",
    "mass": 55.8452,
    "block": "d",
    "boil": 3134,
    "density": 7.874,
    "discoverer": "5000 BC",
    "electron_affinity": 14.785,
    "electron_configuration": "[Ar] 3d6 4s2",
    "electronegativity": 1.83,
    "ionization_energies": [
      762.5,
      1561.9,
      2957,
      5290,
      7240,
      9560,
      12060,
      14580,
      22540,
      25290,
      28000,
      31920,
      34830,
      37840,
      44100,
      47206,
      122200,
      131000,
      140500,
      152600,
      163000,
      173600,
      188100,
      195200,
      851800,
      895161
    ],
    "melt": 1811,
    "molar_heat": 25.1,
    "namer": null,
    "number": 26,
    "period": 4,
    "phase": "Solid",
    "shells": [
      2,
      8,
      14,
      2
    ],
    "group": "Transition Metal",
    "name": "Iron",
    "family": 8
  },
  "Co": {
    "appearance": "hard lustrous gray metal",
    "mass": 58.9331944,
    "block": "d",
    "boil": 3200,
    "density": 8.9,
    "discoverer": "Georg Brandt",
    "electron_affinity": 63.898,
    "electron_configuration": "[Ar] 3d7 4s2",
    "electronegativity": 1.88,
    "ionization_energies": [
      760.4,
      1648,
      3232,
      4950,
      7670,
      9840,
      12440,
      15230,
      17959,
      26570,
      29400,
      32400,
      36600,
      39700,
      42800,
      49396,
      52737,
      134810,
      145170,
      154700,
      167400,
      178100,
      189300,
      204500,
      214100,
      920870,
      966023
    ],
    "melt": 1768,
    "molar_heat": 24.81,
    "namer": null,
    "number": 27,
    "period": 4,
    "phase": "Solid",
    "shells": [
      2,
      8,
      15,
      2
    ],
    "group": "Transition Metal",
    "name": "Cobalt",
    "family": 9
  },
  "Ni": {
    "appearance": "lustrous, metallic, and silver with a gold tinge",
    "mass": 58.69344,
    "block": "d",
    "boil": 3003,
    "density": 8.908,
    "discoverer": "Axel Fredrik Cronstedt",
    "electron_affinity": 111.65,
    "electron_configuration": "[Ar] 3d8 4s2",
    "electronegativity": 1.91,
    "ionization_energies": [
      737.1,
      1753,
      3395,
      5300,
      7339,
      10400,
      12800,
      15600,
      18600,
      21670,
      30970,
      34000,
      37100,
      41500,
      44800,
      48100,
      55101,
      58570,
      148700,
      159000,
      169400,
      182700,
      194000,
      205600,
      221400,
      231490,
      992718,
      1039668
    ],
    "melt": 1728,
    "molar_heat": 26.07,
    "namer": null,
    "number": 28,
    "period": 4,
    "phase": "Solid",
    "shells": [
      2,
      8,
      16,
      2
    ],
    "group": "Transition Metal",
    "name": "Nickel",
    "family": 10
  },
  "Cu": {
    "appearance": "red-orange metallic luster",
    "mass": 63.5463,
    "block": "d",
    "boil": 2835,
    "density": 8.96,
    "discoverer": "Middle East",
    "electron_affinity": 119.235,
    "electron_configuration": "[Ar] 3d10 4s1",
    "electronegativity": 1.9,
    "ionization_energies": [
      745.5,
      1957.9,
      3555,
      5536,
      7700,
      9900,
      13400,
      16000,
      19200,
      22400,
      25600,
      35600,
      38700,
      42000,
      46700,
      50200,
      53700,
      61100,
      64702,
      163700,
      174100,
      184900,
      198800,
      210500,
      222700,
      239100,
      249660,
      1067358,
      1116105
    ],
    "melt": 1357.77,
    "molar_heat": 24.44,
    "namer": null,
    "number": 29,
    "period": 4,
    "phase": "Solid",
    "shells": [
      2,
      8,
      18,
      1
    ],
    "group": "Transition Metal",
    "name": "Copper",
    "family": 11
  },
  "Zn": {
    "appearance": "silver-gray",
    "mass": 65.382,
    "block": "d",
    "boil": 1180,
    "density": 7.14,
    "discoverer": "India",
    "electron_affinity": -58,
    "electron_configuration": "[Ar] 3d10 4s2",
    "electronegativity": 1.65,
    "ionization_energies": [
      906.4,
      1733.3,
      3833,
      5731,
      7970,
      10400,
      12900,
      16800,
      19600,
      23000,
      26400,
      29990,
      40490,
      43800,
      47300,
      52300,
      55900,
      59700,
      67300,
      71200,
      179100
    ],
    "melt": 692.68,
    "molar_heat": 25.47,
    "namer": null,
    "number": 30,
    "period": 4,
    "phase": "Solid",
    "shells": [
      2,
      8,
      18,
      2
    ],
    "group": "Transition Metal",
    "name": "Zinc",
    "family": 12
  },
  "Ga": {
    "appearance": "silver-white",
    "mass": 69.7231,
    "block": "p",
    "boil": 2673,
    "density": 5.91,
    "discoverer": "Lecoq de Boisbaudran",
    "electron_affinity": 41,
    "electron_configuration": "[Ar] 3d10 4s2 4p1",
    "electronegativity": 1.81,
    "ionization_energies": [
      578.8,
      1979.3,
      2963,
      6180
    ],
    "melt": 302.9146,
    "molar_heat": 25.86,
    "namer": null,
    "number": 31,
    "period": 4,
    "phase": "Solid",
    "shells": [
      2,
      8,
      18,
      3
    ],
    "group": "Post-Transition Metal",
    "name": "Gallium",
    "family": 13
  },
  "Ge": {
    "appearance": "grayish-white",
    "mass": 72.6308,
    "block": "p",
    "boil": 3106,
    "density": 5.323,
    "discoverer": "Clemens Winkler",
    "electron_affinity": 118.9352,
    "electron_configuration": "[Ar] 3d10 4s2 4p2",
    "electronegativity": 2.01,
    "ionization_energies": [
      762,
      1537.5,
      3302.1,
      4411,
      9020
    ],
    "melt": 1211.4,
    "molar_heat": 23.222,
    "namer": null,
    "number": 32,
    "period": 4,
    "phase": "Solid",
    "shells": [
      2,
      8,
      18,
      4
    ],
    "group": "Metalloid",
    "name": "Germanium",
    "family": 14
  },
  "As": {
    "appearance": "metallic grey",
    "mass": 74.9215956,
    "block": "p",
    "boil": null,
    "density": 5.727,
    "discoverer": "Bronze Age",
    "electron_affinity": 77.65,
    "electron_configuration": "[Ar] 3d10 4s2 4p3",
    "electronegativity": 2.18,
    "ionization_energies": [
      947,
      1798,
      2735,
      4837,
      6043,
      12310
    ],
    "melt": null,
    "molar_heat": 24.64,
    "namer": null,
    "number": 33,
    "period": 4,
    "phase": "Solid",
    "shells": [
      2,
      8,
      18,
      5
    ],
    "group": "Metalloid",
    "name": "Arsenic",
    "family": 15
  },
  "Se": {
    "appearance": "black, red, and gray (not pictured) allotropes",
    "mass": 78.9718,
    "block": "p",
    "boil": 958,
    "density": 4.81,
    "discoverer": "Jöns Jakob Berzelius",
    "electron_affinity": 194.9587,
    "electron_configuration": "[Ar] 3d10 4s2 4p4",
    "electronegativity": 2.55,
    "ionization_energies": [
      941,
      2045,
      2973.7,
      4144,
      6590,
      7880,
      14990
    ],
    "melt": 494,
    "molar_heat": 25.363,
    "namer": null,
    "number": 34,
    "period": 4,
    "phase": "Solid",
    "shells": [
      2,
      8,
      18,
      6
    ],
    "group": "Polyatomic Non-Metal",
    "name": "Selenium",
    "family": 16
  },
  "Br": {
    "appearance": null,
    "mass": 79.904,
    "block": "p",
    "boil": 332,
    "density": 3.1028,
    "discoverer": "Antoine Jérôme Balard",
    "electron_affinity": 324.537,
    "electron_configuration": "[Ar] 3d10 4s2 4p5",
    "electronegativity": 2.96,
    "ionization_energies": [
      1139.9,
      2103,
      3470,
      4560,
      5760,
      8550,
      9940,
      18600
    ],
    "melt": 265.8,
    "molar_heat": null,
    "namer": null,
    "number": 35,
    "period": 4,
    "phase": "Liquid",
    "shells": [
      2,
      8,
      18,
      7
    ],
    "group": "Diatomic Non-Metal",
    "name": "Bromine",
    "family": 17
  },
  "Kr": {
    "appearance": "colorless gas, exhibiting a whitish glow in a high electric field",
    "mass": 83.7982,
    "block": "p",
    "boil": 119.93,
    "density": 3.749,
    "discoverer": "William Ramsay",
    "electron_affinity": -96,
    "electron_configuration": "[Ar] 3d10 4s2 4p6",
    "electronegativity": 3,
    "ionization_energies": [
      1350.8,
      2350.4,
      3565,
      5070,
      6240,
      7570,
      10710,
      12138,
      22274,
      25880,
      29700,
      33800,
      37700,
      43100,
      47500,
      52200,
      57100,
      61800,
      75800,
      80400,
      85300,
      90400,
      96300,
      101400,
      111100,
      116290,
      282500,
      296200,
      311400,
      326200
    ],
    "melt": 115.78,
    "molar_heat": null,
    "namer": null,
    "number": 36,
    "period": 4,
    "phase": "Gas",
    "shells": [
      2,
      8,
      18,
      8
    ],
    "group": "Noble Gas",
    "name": "Krypton",
    "family": 18
  },
  "Rb": {
    "appearance": "grey white",
    "mass": 85.46783,
    "block": "s",
    "boil": 961,
    "density": 1.532,
    "discoverer": "Robert Bunsen",
    "electron_affinity": 46.884,
    "electron_configuration": "[Kr] 5s1",
    "electronegativity": 0.82,
    "ionization_energies": [
      403,
      2633,
      3860,
      5080,
      6850,
      8140,
      9570,
      13120,
      14500,
      26740
    ],
    "melt": 312.45,
    "molar_heat": 31.06,
    "namer": null,
    "number": 37,
    "period": 5,
    "phase": "Solid",
    "shells": [
      2,
      8,
      18,
      8,
      1
    ],
    "group": "Alkali Metal",
    "name": "Rubidium",
    "family": 1
  },
  "Sr": {
    "appearance": null,
    "mass": 87.621,
    "block": "s",
    "boil": 1650,
    "density": 2.64,
    "discoverer": "William Cruickshank (chemist)",
    "electron_affinity": 5.023,
    "electron_configuration": "[Kr] 5s2",
    "electronegativity": 0.95,
    "ionization_energies": [
      549.5,
      1064.2,
      4138,
      5500,
      6910,
      8760,
      10230,
      11800,
      15600,
      17100,
      31270
    ],
    "melt": 1050,
    "molar_heat": 26.4,
    "namer": null,
    "number": 38,
    "period": 5,
    "phase": "Solid",
    "shells": [
      2,
      8,
      18,
      8,
      2
    ],
    "group": "Alkaline Earth Metal",
    "name": "Strontium",
    "family": 2
  },
  "Y": {
    "appearance": "silvery white",
    "mass": 88.905842,
    "block": "d",
    "boil": 3203,
    "density": 4.472,
    "discoverer": "Johan Gadolin",
    "electron_affinity": 29.6,
    "electron_configuration": "[Kr] 4d1 5s2",
    "electronegativity": 1.22,
    "ionization_energies": [
      600,
      1180,
      1980,
      5847,
      7430,
      8970,
      11190,
      12450,
      14110,
      18400,
      19900,
      36090
    ],
    "melt": 1799,
    "molar_heat": 26.53,
    "namer": null,
    "number": 39,
    "period": 5,
    "phase": "Solid",
    "shells": [
      2,
      8,
      18,
      9,
      2
    ],
    "group": "Transition Metal",
    "name": "Yttrium",
    "family": 3
  },
  "Zr": {
    "appearance": "silvery white",
    "mass": 91.2242,
    "block": "d",
    "boil": 4650,
    "density": 6.52,
    "discoverer": "Martin Heinrich Klaproth",
    "electron_affinity": 41.806,
    "electron_configuration": "[Kr] 4d2 5s2",
    "electronegativity": 1.33,
    "ionization_energies": [
      640.1,
      1270,
      2218,
      3313,
      7752,
      9500
    ],
    "melt": 2128,
    "molar_heat": 25.36,
    "namer": null,
    "number": 40,
    "period": 5,
    "phase": "Solid",
    "shells": [
      2,
      8,
      18,
      10,
      2
    ],
    "group": "Transition Metal",
    "name": "Zirconium",
    "family": 4
  },
  "Nb": {
    "appearance": "gray metallic, bluish when oxidized",
    "mass": 92.906372,
    "block": "d",
    "boil": 5017,
    "density": 8.57,
    "discoverer": "Charles Hatchett",
    "electron_affinity": 88.516,
    "electron_configuration": "[Kr] 4d4 5s1",
    "electronegativity": 1.6,
    "ionization_energies": [
      652.1,
      1380,
      2416,
      3700,
      4877,
      9847,
      12100
    ],
    "melt": 2750,
    "molar_heat": 24.6,
    "namer": null,
    "number": 41,
    "period": 5,
    "phase": "Solid",
    "shells": [
      2,
      8,
      18,
      12,
      1
    ],
    "group": "Transition Metal",
    "name": "Niobium",
    "family": 5
  },
  "Mo": {
    "appearance": "gray metallic",
    "mass": 95.951,
    "block": "d",
    "boil": 4912,
    "density": 10.28,
    "discoverer": "Carl Wilhelm Scheele",
    "electron_affinity": 72.1,
    "electron_configuration": "[Kr] 4d5 5s1",
    "electronegativity": 2.16,
    "ionization_energies": [
      684.3,
      1560,
      2618,
      4480,
      5257,
      6640.8,
      12125,
      13860,
      15835,
      17980,
      20190,
      22219,
      26930,
      29196,
      52490,
      55000,
      61400,
      67700,
      74000,
      80400,
      87000,
      93400,
      98420,
      104400,
      121900,
      127700,
      133800,
      139800,
      148100,
      154500
    ],
    "melt": 2896,
    "molar_heat": 24.06,
    "namer": null,
    "number": 42,
    "period": 5,
    "phase": "Solid",
    "shells": [
      2,
      8,
      18,
      13,
      1
    ],
    "group": "Transition Metal",
    "name": "Molybdenum",
    "family": 6
  },
  "Tc": {
    "appearance": "shiny gray metal",
    "mass": 98,
    "block": "d",
    "boil": 4538,
    "density": 11,
    "discoverer": "Emilio Segrè",
    "electron_affinity": 53,
    "electron_configuration": "[Kr] 4d5 5s2",
    "electronegativity": 1.9,
    "ionization_energies": [
      702,
      1470,
      2850
    ],
    "melt": 2430,
    "molar_heat": 24.27,
    "namer": null,
    "number": 43,
    "period": 5,
    "phase": "Solid",
    "shells": [
      2,
      8,
      18,
      13,
      2
    ],
    "group": "Transition Metal",
    "name": "Technetium",
    "family": 7
  },
  "Ru": {
    "appearance": "silvery white metallic",
    "mass": 101.072,
    "block": "d",
    "boil": 4423,
    "density": 12.45,
    "discoverer": "Karl Ernst Claus",
    "electron_affinity": 100.96,
    "electron_configuration": "[Kr] 4d7 5s1",
    "electronegativity": 2.2,
    "ionization_energies": [
      710.2,
      1620,
      2747
    ],
    "melt": 2607,
    "molar_heat": 24.06,
    "namer": null,
    "number": 44,
    "period": 5,
    "phase": "Solid",
    "shells": [
      2,
      8,
      18,
      15,
      1
    ],
    "group": "Transition Metal",
    "name": "Ruthenium",
    "family": 8
  },
  "Rh": {
    "appearance": "silvery white metallic",
    "mass": 102.905502,
    "block": "d",
    "boil": 3968,
    "density": 12.41,
    "discoverer": "William Hyde Wollaston",
    "electron_affinity": 110.27,
    "electron_configuration": "[Kr] 4d8 5s1",
    "electronegativity": 2.28,
    "ionization_energies": [
      719.7,
      1740,
      2997
    ],
    "melt": 2237,
    "molar_heat": 24.98,
    "namer": null,
    "number": 45,
    "period": 5,
    "phase": "Solid",
    "shells": [
      2,
      8,
      18,
      16,
      1
    ],
    "group": "Transition Metal",
    "name": "Rhodium",
    "family": 9
  },
  "Pd": {
    "appearance": "silvery white",
    "mass": 106.421,
    "block": "d",
    "boil": 3236,
    "density": 12.023,
    "discoverer": "William Hyde Wollaston",
    "electron_affinity": 54.24,
    "electron_configuration": "[Kr] 4d10",
    "electronegativity": 2.2,
    "ionization_energies": [
      804.4,
      1870,
      3177
    ],
    "melt": 1828.05,
    "molar_heat": 25.98,
    "namer": null,
    "number": 46,
    "period": 5,
    "phase": "Solid",
    "shells": [
      2,
      8,
      18,
      18
    ],
    "group": "Transition Metal",
    "name": "Palladium",
    "family": 10
  },
  "Ag": {
    "appearance": "lustrous white metal",
    "mass": 107.86822,
    "block": "d",
    "boil": 2435,
    "density": 10.49,
    "discoverer": "unknown, before 5000 BC",
    "electron_affinity": 125.862,
    "electron_configuration": "[Kr] 4d10 5s1",
    "electronegativity": 1.93,
    "ionization_energies": [
      731,
      2070,
      3361
    ],
    "melt": 1234.93,
    "molar_heat": 25.35,
    "namer": null,
    "number": 47,
    "period": 5,
    "phase": "Solid",
    "shells": [
      2,
      8,
      18,
      18,
      1
    ],
    "group": "Transition Metal",
    "name": "Silver",
    "family": 11
  },
  "Cd": {
    "appearance": "silvery bluish-gray metallic",
    "mass": 112.4144,
    "block": "d",
    "boil": 1040,
    "density": 8.65,
    "discoverer": "Karl Samuel Leberecht Hermann",
    "electron_affinity": -68,
    "electron_configuration": "[Kr] 4d10 5s2",
    "electronegativity": 1.69,
    "ionization_energies": [
      867.8,
      1631.4,
      3616
    ],
    "melt": 594.22,
    "molar_heat": 26.02,
    "namer": "Isotopes of cadmium",
    "number": 48,
    "period": 5,
    "phase": "Solid",
    "shells": [
      2,
      8,
      18,
      18,
      2
    ],
    "group": "Transition Metal",
    "name": "Cadmium",
    "family": 12
  },
  "In": {
    "appearance": "silvery lustrous gray",
    "mass": 114.8181,
    "block": "p",
    "boil": 2345,
    "density": 7.31,
    "discoverer": "Ferdinand Reich",
    "electron_affinity": 37.043,
    "electron_configuration": "[Kr] 4d10 5s2 5p1",
    "electronegativity": 1.78,
    "ionization_energies": [
      558.3,
      1820.7,
      2704,
      5210
    ],
    "melt": 429.7485,
    "molar_heat": 26.74,
    "namer": null,
    "number": 49,
    "period": 5,
    "phase": "Solid",
    "shells": [
      2,
      8,
      18,
      18,
      3
    ],
    "group": "Post-Transition Metal",
    "name": "Indium",
    "family": 13
  },
  "Sn": {
    "appearance": "silvery-white (beta, β) or gray (alpha, α)",
    "mass": 118.7107,
    "block": "p",
    "boil": 2875,
    "density": 7.365,
    "discoverer": "unknown, before 3500 BC",
    "electron_affinity": 107.2984,
    "electron_configuration": "[Kr] 4d10 5s2 5p2",
    "electronegativity": 1.96,
    "ionization_energies": [
      708.6,
      1411.8,
      2943,
      3930.3,
      7456
    ],
    "melt": 505.08,
    "molar_heat": 27.112,
    "namer": null,
    "number": 50,
    "period": 5,
    "phase": "Solid",
    "shells": [
      2,
      8,
      18,
      18,
      4
    ],
    "group": "Post-Transition Metal",
    "name": "Tin",
    "family": 14
  },
  "Sb": {
    "appearance": "silvery lustrous gray",
    "mass": 121.7601,
    "block": "p",
    "boil": 1908,
    "density": 6.697,
    "discoverer": "unknown, before 3000 BC",
    "electron_affinity": 101.059,
    "electron_configuration": "[Kr] 4d10 5s2 5p3",
    "electronegativity": 2.05,
    "ionization_energies": [
      834,
      1594.9,
      2440,
      4260,
      5400,
      10400
    ],
    "melt": 903.78,
    "molar_heat": 25.23,
    "namer": null,
    "number": 51,
    "period": 5,
    "phase": "Solid",
    "shells": [
      2,
      8,
      18,
      18,
      5
    ],
    "group": "Metalloid",
    "name": "Antimony",
    "family": 15
  },
  "Te": {
    "appearance": null,
    "mass": 127.603,
    "block": "p",
    "boil": 1261,
    "density": 6.24,
    "discoverer": "Franz-Joseph Müller von Reichenstein",
    "electron_affinity": 190.161,
    "electron_configuration": "[Kr] 4d10 5s2 5p4",
    "electronegativity": 2.1,
    "ionization_energies": [
      869.3,
      1790,
      2698,
      3610,
      5668,
      6820,
      13200
    ],
    "melt": 722.66,
    "molar_heat": 25.73,
    "namer": null,
    "number": 52,
    "period": 5,
    "phase": "Solid",
    "shells": [
      2,
      8,
      18,
      18,
      6
    ],
    "group": "Metalloid",
    "name": "Tellurium",
    "family": 16
  },
  "I": {
    "appearance": "lustrous metallic gray, violet as a gas",
    "mass": 126.904473,
    "block": "p",
    "boil": 457.4,
    "density": 4.933,
    "discoverer": "Bernard Courtois",
    "electron_affinity": 295.1531,
    "electron_configuration": "[Kr] 4d10 5s2 5p5",
    "electronegativity": 2.66,
    "ionization_energies": [
      1008.4,
      1845.9,
      3180
    ],
    "melt": 386.85,
    "molar_heat": null,
    "namer": null,
    "number": 53,
    "period": 5,
    "phase": "Solid",
    "shells": [
      2,
      8,
      18,
      18,
      7
    ],
    "group": "Diatomic Non-Metal",
    "name": "Iodine",
    "family": 17
  },
  "Xe": {
    "appearance": "colorless gas, exhibiting a blue glow when placed in a high voltage electric field",
    "mass": 131.2936,
    "block": "p",
    "boil": 165.051,
    "density": 5.894,
    "discoverer": "William Ramsay",
    "electron_affinity": -77,
    "electron_configuration": "[Kr] 4d10 5s2 5p6",
    "electronegativity": 2.6,
    "ionization_energies": [
      1170.4,
      2046.4,
      3099.4
    ],
    "melt": 161.4,
    "molar_heat": null,
    "namer": null,
    "number": 54,
    "period": 5,
    "phase": "Gas",
    "shells": [
      2,
      8,
      18,
      18,
      8
    ],
    "group": "Noble Gas",
    "name": "Xenon",
    "family": 18
  },
  "Cs": {
    "appearance": "silvery gold",
    "mass": 132.905451966,
    "block": "s",
    "boil": 944,
    "density": 1.93,
    "discoverer": "Robert Bunsen",
    "electron_affinity": 45.505,
    "electron_configuration": "[Xe] 6s1",
    "electronegativity": 0.79,
    "ionization_energies": [
      375.7,
      2234.3,
      3400
    ],
    "melt": 301.7,
    "molar_heat": 32.21,
    "namer": null,
    "number": 55,
    "period": 6,
    "phase": "Solid",
    "shells": [
      2,
      8,
      18,
      18,
      8,
      1
    ],
    "group": "Alkali Metal",
    "name": "Cesium",
    "family": 1
  },
  "Ba": {
    "appearance": null,
    "mass": 137.3277,
    "block": "s",
    "boil": 2118,
    "density": 3.51,
    "discoverer": "Carl Wilhelm Scheele",
    "electron_affinity": 13.954,
    "electron_configuration": "[Xe] 6s2",
    "electronegativity": 0.89,
    "ionization_energies": [
      502.9,
      965.2,
      3600
    ],
    "melt": 1000,
    "molar_heat": 28.07,
    "namer": null,
    "number": 56,
    "period": 6,
    "phase": "Solid",
    "shells": [
      2,
      8,
      18,
      18,
      8,
      2
    ],
    "group": "Alkaline Earth Metal",
    "name": "Barium",
    "family": 2
  },
  "La": {
    "appearance": "silvery white",
    "mass": 138.905477,
    "block": "f",
    "boil": 3737,
    "density": 6.162,
    "discoverer": "Carl Gustaf Mosander",
    "electron_affinity": 53,
    "electron_configuration": "[Xe] 5d16s2",
    "electronegativity": 1.1,
    "ionization_energies": [
      538.1,
      1067,
      1850.3,
      4819,
      5940
    ],
    "melt": 1193,
    "molar_heat": 27.11,
    "namer": null,
    "number": 57,
    "period": 6,
    "phase": "Solid",
    "shells": [
      2,
      8,
      18,
      18,
      9,
      2
    ],
    "group": "Lanthanide",
    "name": "Lanthanum",
    "family": 3
  },
  "Ce": {
    "appearance": "silvery white",
    "mass": 140.1161,
    "block": "f",
    "boil": 3716,
    "density": 6.77,
    "discoverer": "Martin Heinrich Klaproth",
    "electron_affinity": 55,
    "electron_configuration": "[Xe] 4f1 5d1 6s2",
    "electronegativity": 1.12,
    "ionization_energies": [
      534.4,
      1050,
      1949,
      3547,
      6325,
      7490
    ],
    "melt": 1068,
    "molar_heat": 26.94,
    "namer": null,
    "number": 58,
    "period": 6,
    "phase": "Solid",
    "shells": [
      2,
      8,
      18,
      19,
      9,
      2
    ],
    "group": "Lanthanide",
    "name": "Cerium",
    "family": 3
  },
  "Pr": {
    "appearance": "grayish white",
    "mass": 140.907662,
    "block": "f",
    "boil": 3403,
    "density": 6.77,
    "discoverer": "Carl Auer von Welsbach",
    "electron_affinity": 93,
    "electron_configuration": "[Xe] 4f3 6s2",
    "electronegativity": 1.13,
    "ionization_energies": [
      527,
      1020,
      2086,
      3761,
      5551
    ],
    "melt": 1208,
    "molar_heat": 27.2,
    "namer": null,
    "number": 59,
    "period": 6,
    "phase": "Solid",
    "shells": [
      2,
      8,
      18,
      21,
      8,
      2
    ],
    "group": "Lanthanide",
    "name": "Praseodymium",
    "family": 3
  },
  "Nd": {
    "appearance": "silvery white",
    "mass": 144.2423,
    "block": "f",
    "boil": 3347,
    "density": 7.01,
    "discoverer": "Carl Auer von Welsbach",
    "electron_affinity": 184.87,
    "electron_configuration": "[Xe] 4f4 6s2",
    "electronegativity": 1.14,
    "ionization_energies": [
      533.1,
      1040,
      2130,
      3900
    ],
    "melt": 1297,
    "molar_heat": 27.45,
    "namer": null,
    "number": 60,
    "period": 6,
    "phase": "Solid",
    "shells": [
      2,
      8,
      18,
      22,
      8,
      2
    ],
    "group": "Lanthanide",
    "name": "Neodymium",
    "family": 3
  },
  "Pm": {
    "appearance": "metallic",
    "mass": 145,
    "block": "f",
    "boil": 3273,
    "density": 7.26,
    "discoverer": "Chien Shiung Wu",
    "electron_affinity": 12.45,
    "electron_configuration": "[Xe] 4f5 6s2",
    "electronegativity": 1.13,
    "ionization_energies": [
      540,
      1050,
      2150,
      3970
    ],
    "melt": 1315,
    "molar_heat": null,
    "namer": "Isotopes of promethium",
    "number": 61,
    "period": 6,
    "phase": "Solid",
    "shells": [
      2,
      8,
      18,
      23,
      8,
      2
    ],
    "group": "Lanthanide",
    "name": "Promethium",
    "family": 3
  },
  "Sm": {
    "appearance": "silvery white",
    "mass": 150.362,
    "block": "f",
    "boil": 2173,
    "density": 7.52,
    "discoverer": "Lecoq de Boisbaudran",
    "electron_affinity": 15.63,
    "electron_configuration": "[Xe] 4f6 6s2",
    "electronegativity": 1.17,
    "ionization_energies": [
      544.5,
      1070,
      2260,
      3990
    ],
    "melt": 1345,
    "molar_heat": 29.54,
    "namer": null,
    "number": 62,
    "period": 6,
    "phase": "Solid",
    "shells": [
      2,
      8,
      18,
      24,
      8,
      2
    ],
    "group": "Lanthanide",
    "name": "Samarium",
    "family": 3
  },
  "Eu": {
    "appearance": null,
    "mass": 151.9641,
    "block": "f",
    "boil": 1802,
    "density": 5.264,
    "discoverer": "Eugène-Anatole Demarçay",
    "electron_affinity": 11.2,
    "electron_configuration": "[Xe] 4f7 6s2",
    "electronegativity": 1.2,
    "ionization_energies": [
      547.1,
      1085,
      2404,
      4120
    ],
    "melt": 1099,
    "molar_heat": 27.66,
    "namer": null,
    "number": 63,
    "period": 6,
    "phase": "Solid",
    "shells": [
      2,
      8,
      18,
      25,
      8,
      2
    ],
    "group": "Lanthanide",
    "name": "Europium",
    "family": 3
  },
  "Gd": {
    "appearance": "silvery white",
    "mass": 157.253,
    "block": "f",
    "boil": 3273,
    "density": 7.9,
    "discoverer": "Jean Charles Galissard de Marignac",
    "electron_affinity": 13.22,
    "electron_configuration": "[Xe] 4f7 5d1 6s2",
    "electronegativity": 1.2,
    "ionization_energies": [
      593.4,
      1170,
      1990,
      4250
    ],
    "melt": 1585,
    "molar_heat": 37.03,
    "namer": null,
    "number": 64,
    "period": 6,
    "phase": "Solid",
    "shells": [
      2,
      8,
      18,
      25,
      9,
      2
    ],
    "group": "Lanthanide",
    "name": "Gadolinium",
    "family": 3
  },
  "Tb": {
    "appearance": "silvery white",
    "mass": 158.925352,
    "block": "f",
    "boil": 3396,
    "density": 8.23,
    "discoverer": "Carl Gustaf Mosander",
    "electron_affinity": 112.4,
    "electron_configuration": "[Xe] 4f9 6s2",
    "electronegativity": 1.1,
    "ionization_energies": [
      565.8,
      1110,
      2114,
      3839
    ],
    "melt": 1629,
    "molar_heat": 28.91,
    "namer": null,
    "number": 65,
    "period": 6,
    "phase": "Solid",
    "shells": [
      2,
      8,
      18,
      27,
      8,
      2
    ],
    "group": "Lanthanide",
    "name": "Terbium",
    "family": 3
  },
  "Dy": {
    "appearance": "silvery white",
    "mass": 162.5001,
    "block": "f",
    "boil": 2840,
    "density": 8.54,
    "discoverer": "Lecoq de Boisbaudran",
    "electron_affinity": 33.96,
    "electron_configuration": "[Xe] 4f10 6s2",
    "electronegativity": 1.22,
    "ionization_energies": [
      573,
      1130,
      2200,
      3990
    ],
    "melt": 1680,
    "molar_heat": 27.7,
    "namer": null,
    "number": 66,
    "period": 6,
    "phase": "Solid",
    "shells": [
      2,
      8,
      18,
      28,
      8,
      2
    ],
    "group": "Lanthanide",
    "name": "Dysprosium",
    "family": 3
  },
  "Ho": {
    "appearance": "silvery white",
    "mass": 164.930332,
    "block": "f",
    "boil": 2873,
    "density": 8.79,
    "discoverer": "Marc Delafontaine",
    "electron_affinity": 32.61,
    "electron_configuration": "[Xe] 4f11 6s2",
    "electronegativity": 1.23,
    "ionization_energies": [
      581,
      1140,
      2204,
      4100
    ],
    "melt": 1734,
    "molar_heat": 27.15,
    "namer": null,
    "number": 67,
    "period": 6,
    "phase": "Solid",
    "shells": [
      2,
      8,
      18,
      29,
      8,
      2
    ],
    "group": "Lanthanide",
    "name": "Holmium",
    "family": 3
  },
  "Er": {
    "appearance": "silvery white",
    "mass": 167.2593,
    "block": "f",
    "boil": 3141,
    "density": 9.066,
    "discoverer": "Carl Gustaf Mosander",
    "electron_affinity": 30.1,
    "electron_configuration": "[Xe] 4f12 6s2",
    "electronegativity": 1.24,
    "ionization_energies": [
      589.3,
      1150,
      2194,
      4120
    ],
    "melt": 1802,
    "molar_heat": 28.12,
    "namer": null,
    "number": 68,
    "period": 6,
    "phase": "Solid",
    "shells": [
      2,
      8,
      18,
      30,
      8,
      2
    ],
    "group": "Lanthanide",
    "name": "Erbium",
    "family": 3
  },
  "Tm": {
    "appearance": "silvery gray",
    "mass": 168.934222,
    "block": "f",
    "boil": 2223,
    "density": 9.32,
    "discoverer": "Per Teodor Cleve",
    "electron_affinity": 99,
    "electron_configuration": "[Xe] 4f13 6s2",
    "electronegativity": 1.25,
    "ionization_energies": [
      596.7,
      1160,
      2285,
      4120
    ],
    "melt": 1818,
    "molar_heat": 27.03,
    "namer": null,
    "number": 69,
    "period": 6,
    "phase": "Solid",
    "shells": [
      2,
      8,
      18,
      31,
      8,
      2
    ],
    "group": "Lanthanide",
    "name": "Thulium",
    "family": 3
  },
  "Yb": {
    "appearance": null,
    "mass": 173.0451,
    "block": "f",
    "boil": 1469,
    "density": 6.9,
    "discoverer": "Jean Charles Galissard de Marignac",
    "electron_affinity": -1.93,
    "electron_configuration": "[Xe] 4f14 6s2",
    "electronegativity": 1.1,
    "ionization_energies": [
      603.4,
      1174.8,
      2417,
      4203
    ],
    "melt": 1097,
    "molar_heat": 26.74,
    "namer": null,
    "number": 70,
    "period": 6,
    "phase": "Solid",
    "shells": [
      2,
      8,
      18,
      32,
      8,
      2
    ],
    "group": "Lanthanide",
    "name": "Ytterbium",
    "family": 3
  },
  "Lu": {
    "appearance": "silvery white",
    "mass": 174.96681,
    "block": "d",
    "boil": 3675,
    "density": 9.841,
    "discoverer": "Georges Urbain",
    "electron_affinity": 33.4,
    "electron_configuration": "[Xe] 4f14 5d1 6s2",
    "electronegativity": 1.27,
    "ionization_energies": [
      523.5,
      1340,
      2022.3,
      4370,
      6445
    ],
    "melt": 1925,
    "molar_heat": 26.86,
    "namer": null,
    "number": 71,
    "period": 6,
    "phase": "Solid",
    "shells": [
      2,
      8,
      18,
      32,
      9,
      2
    ],
    "group": "Lanthanide",
    "name": "Lutetium",
    "family": 3
  },
  "Hf": {
    "appearance": "steel gray",
    "mass": 178.492,
    "block": "d",
    "boil": 4876,
    "density": 13.31,
    "discoverer": "Dirk Coster",
    "electron_affinity": 17.18,
    "electron_configuration": "[Xe] 4f14 5d2 6s2",
    "electronegativity": 1.3,
    "ionization_energies": [
      658.5,
      1440,
      2250,
      3216
    ],
    "melt": 2506,
    "molar_heat": 25.73,
    "namer": null,
    "number": 72,
    "period": 6,
    "phase": "Solid",
    "shells": [
      2,
      8,
      18,
      32,
      10,
      2
    ],
    "group": "Transition Metal",
    "name": "Hafnium",
    "family": 4
  },
  "Ta": {
    "appearance": "gray blue",
    "mass": 180.947882,
    "block": "d",
    "boil": 5731,
    "density": 16.69,
    "discoverer": "Anders Gustaf Ekeberg",
    "electron_affinity": 31,
    "electron_configuration": "[Xe] 4f14 5d3 6s2",
    "electronegativity": 1.5,
    "ionization_energies": [
      761,
      1500
    ],
    "melt": 3290,
    "molar_heat": 25.36,
    "namer": null,
    "number": 73,
    "period": 6,
    "phase": "Solid",
    "shells": [
      2,
      8,
      18,
      32,
      11,
      2
    ],
    "group": "Transition Metal",
    "name": "Tantalum",
    "family": 5
  },
  "W": {
    "appearance": "grayish white, lustrous",
    "mass": 183.841,
    "block": "d",
    "boil": 6203,
    "density": 19.25,
    "discoverer": "Carl Wilhelm Scheele",
    "electron_affinity": 78.76,
    "electron_configuration": "[Xe] 4f14 5d4 6s2",
    "electronegativity": 2.36,
    "ionization_energies": [
      770,
      1700
    ],
    "melt": 3695,
    "molar_heat": 24.27,
    "namer": null,
    "number": 74,
    "period": 6,
    "phase": "Solid",
    "shells": [
      2,
      8,
      18,
      32,
      12,
      2
    ],
    "group": "Transition Metal",
    "name": "Tungsten",
    "family": 6
  },
  "Re": {
    "appearance": "silvery-grayish",
    "mass": 186.2071,
    "block": "d",
    "boil": 5869,
    "density": 21.02,
    "discoverer": "Masataka Ogawa",
    "electron_affinity": 5.8273,
    "electron_configuration": "[Xe] 4f14 5d5 6s2",
    "electronegativity": 1.9,
    "ionization_energies": [
      760,
      1260,
      2510,
      3640
    ],
    "melt": 3459,
    "molar_heat": 25.48,
    "namer": "Walter Noddack",
    "number": 75,
    "period": 6,
    "phase": "Solid",
    "shells": [
      2,
      8,
      18,
      32,
      13,
      2
    ],
    "group": "Transition Metal",
    "name": "Rhenium",
    "family": 7
  },
  "Os": {
    "appearance": "silvery, blue cast",
    "mass": 190.233,
    "block": "d",
    "boil": 5285,
    "density": 22.59,
    "discoverer": "Smithson Tennant",
    "electron_affinity": 103.99,
    "electron_configuration": "[Xe] 4f14 5d6 6s2",
    "electronegativity": 2.2,
    "ionization_energies": [
      840,
      1600
    ],
    "melt": 3306,
    "molar_heat": 24.7,
    "namer": null,
    "number": 76,
    "period": 6,
    "phase": "Solid",
    "shells": [
      2,
      8,
      18,
      32,
      14,
      2
    ],
    "group": "Transition Metal",
    "name": "Osmium",
    "family": 8
  },
  "Ir": {
    "appearance": "silvery white",
    "mass": 192.2173,
    "block": "d",
    "boil": 4403,
    "density": 22.56,
    "discoverer": "Smithson Tennant",
    "electron_affinity": 150.94,
    "electron_configuration": "[Xe] 4f14 5d7 6s2",
    "electronegativity": 2.2,
    "ionization_energies": [
      880,
      1600
    ],
    "melt": 2719,
    "molar_heat": 25.1,
    "namer": null,
    "number": 77,
    "period": 6,
    "phase": "Solid",
    "shells": [
      2,
      8,
      18,
      32,
      15,
      2
    ],
    "group": "Transition Metal",
    "name": "Iridium",
    "family": 9
  },
  "Pt": {
    "appearance": "silvery white",
    "mass": 195.0849,
    "block": "d",
    "boil": 4098,
    "density": 21.45,
    "discoverer": "Antonio de Ulloa",
    "electron_affinity": 205.041,
    "electron_configuration": "[Xe] 4f14 5d9 6s1",
    "electronegativity": 2.28,
    "ionization_energies": [
      870,
      1791
    ],
    "melt": 2041.4,
    "molar_heat": 25.86,
    "namer": null,
    "number": 78,
    "period": 6,
    "phase": "Solid",
    "shells": [
      2,
      8,
      18,
      32,
      17,
      1
    ],
    "group": "Transition Metal",
    "name": "Platinum",
    "family": 10
  },
  "Au": {
    "appearance": "metallic yellow",
    "mass": 196.9665695,
    "block": "d",
    "boil": 3243,
    "density": 19.3,
    "discoverer": "Middle East",
    "electron_affinity": 222.747,
    "electron_configuration": "[Xe] 4f14 5d10 6s1",
    "electronegativity": 2.54,
    "ionization_energies": [
      890.1,
      1980
    ],
    "melt": 1337.33,
    "molar_heat": 25.418,
    "namer": null,
    "number": 79,
    "period": 6,
    "phase": "Solid",
    "shells": [
      2,
      8,
      18,
      32,
      18,
      1
    ],
    "group": "Transition Metal",
    "name": "Gold",
    "family": 11
  },
  "Hg": {
    "appearance": "silvery",
    "mass": 200.5923,
    "block": "d",
    "boil": 629.88,
    "density": 13.534,
    "discoverer": "unknown, before 2000 BCE",
    "electron_affinity": -48,
    "electron_configuration": "[Xe] 4f14 5d10 6s2",
    "electronegativity": 2,
    "ionization_energies": [
      1007.1,
      1810,
      3300
    ],
    "melt": 234.321,
    "molar_heat": 27.983,
    "namer": null,
    "number": 80,
    "period": 6,
    "phase": "Liquid",
    "shells": [
      2,
      8,
      18,
      32,
      18,
      2
    ],
    "group": "Transition Metal",
    "name": "Mercury",
    "family": 12
  },
  "Tl": {
    "appearance": "silvery white",
    "mass": 204.38,
    "block": "p",
    "boil": 1746,
    "density": 11.85,
    "discoverer": "William Crookes",
    "electron_affinity": 36.4,
    "electron_configuration": "[Xe] 4f14 5d10 6s2 6p1",
    "electronegativity": 1.62,
    "ionization_energies": [
      589.4,
      1971,
      2878
    ],
    "melt": 577,
    "molar_heat": 26.32,
    "namer": null,
    "number": 81,
    "period": 6,
    "phase": "Solid",
    "shells": [
      2,
      8,
      18,
      32,
      18,
      3
    ],
    "group": "Post-Transition Metal",
    "name": "Thallium",
    "family": 13
  },
  "Pb": {
    "appearance": "metallic gray",
    "mass": 207.21,
    "block": "p",
    "boil": 2022,
    "density": 11.34,
    "discoverer": "Middle East",
    "electron_affinity": 34.4204,
    "electron_configuration": "[Xe] 4f14 5d10 6s2 6p2",
    "electronegativity": 1.87,
    "ionization_energies": [
      715.6,
      1450.5,
      3081.5,
      4083,
      6640
    ],
    "melt": 600.61,
    "molar_heat": 26.65,
    "namer": null,
    "number": 82,
    "period": 6,
    "phase": "Solid",
    "shells": [
      2,
      8,
      18,
      32,
      18,
      4
    ],
    "group": "Post-Transition Metal",
    "name": "Lead",
    "family": 14
  },
  "Bi": {
    "appearance": "lustrous silver",
    "mass": 208.980401,
    "block": "p",
    "boil": 1837,
    "density": 9.78,
    "discoverer": "Claude François Geoffroy",
    "electron_affinity": 90.924,
    "electron_configuration": "[Xe] 4f14 5d10 6s2 6p3",
    "electronegativity": 2.02,
    "ionization_energies": [
      703,
      1610,
      2466,
      4370,
      5400,
      8520
    ],
    "melt": 544.7,
    "molar_heat": 25.52,
    "namer": null,
    "number": 83,
    "period": 6,
    "phase": "Solid",
    "shells": [
      2,
      8,
      18,
      32,
      18,
      5
    ],
    "group": "Post-Transition Metal",
    "name": "Bismuth",
    "family": 15
  },
  "Po": {
    "appearance": "silvery",
    "mass": 209,
    "block": "p",
    "boil": 1235,
    "density": 9.196,
    "discoverer": "Pierre Curie",
    "electron_affinity": 136,
    "electron_configuration": "[Xe] 4f14 5d10 6s2 6p4",
    "electronegativity": 2,
    "ionization_energies": [
      812.1
    ],
    "melt": 527,
    "molar_heat": 26.4,
    "namer": null,
    "number": 84,
    "period": 6,
    "phase": "Solid",
    "shells": [
      2,
      8,
      18,
      32,
      18,
      6
    ],
    "group": "Post-Transition Metal",
    "name": "Polonium",
    "family": 16
  },
  "At": {
    "appearance": "unknown, probably metallic",
    "mass": 210,
    "block": "p",
    "boil": 610,
    "density": 6.35,
    "discoverer": "Dale R. Corson",
    "electron_affinity": 233,
    "electron_configuration": "[Xe] 4f14 5d10 6s2 6p5",
    "electronegativity": 2.2,
    "ionization_energies": [
      899.003
    ],
    "melt": 575,
    "molar_heat": null,
    "namer": null,
    "number": 85,
    "period": 6,
    "phase": "Solid",
    "shells": [
      2,
      8,
      18,
      32,
      18,
      7
    ],
    "group": "Metalloid",
    "name": "Astatine",
    "family": 17
  },
  "Rn": {
    "appearance": "colorless gas, occasionally glows green or red in discharge tubes",
    "mass": 222,
    "block": "p",
    "boil": 211.5,
    "density": 9.73,
    "discoverer": "Friedrich Ernst Dorn",
    "electron_affinity": -68,
    "electron_configuration": "[Xe] 4f14 5d10 6s2 6p6",
    "electronegativity": 2.2,
    "ionization_energies": [
      1037
    ],
    "melt": 202,
    "molar_heat": null,
    "namer": null,
    "number": 86,
    "period": 6,
    "phase": "Gas",
    "shells": [
      2,
      8,
      18,
      32,
      18,
      8
    ],
    "group": "Noble Gas",
    "name": "Radon",
    "family": 18
  },
  "Fr": {
    "appearance": null,
    "mass": 223,
    "block": "s",
    "boil": 950,
    "density": 1.87,
    "discoverer": "Marguerite Perey",
    "electron_affinity": 46.89,
    "electron_configuration": "[Rn] 7s1",
    "electronegativity": 0.79,
    "ionization_energies": [
      380
    ],
    "melt": 300,
    "molar_heat": null,
    "namer": null,
    "number": 87,
    "period": 7,
    "phase": "Solid",
    "shells": [
      2,
      8,
      18,
      32,
      18,
      8,
      1
    ],
    "group": "Alkali Metal",
    "name": "Francium",
    "family": 1
  },
  "Ra": {
    "appearance": "silvery white metallic",
    "mass": 226,
    "block": "s",
    "boil": 2010,
    "density": 5.5,
    "discoverer": "Pierre Curie",
    "electron_affinity": 9.6485,
    "electron_configuration": "[Rn] 7s2",
    "electronegativity": 0.9,
    "ionization_energies": [
      509.3,
      979
    ],
    "melt": 1233,
    "molar_heat": null,
    "namer": null,
    "number": 88,
    "period": 7,
    "phase": "Solid",
    "shells": [
      2,
      8,
      18,
      32,
      18,
      8,
      2
    ],
    "group": "Alkaline Earth Metal",
    "name": "Radium",
    "family": 2
  },
  "Ac": {
    "appearance": null,
    "mass": 227,
    "block": "f",
    "boil": 3500,
    "density": 10,
    "discoverer": "Friedrich Oskar Giesel",
    "electron_affinity": 33.77,
    "electron_configuration": "[Rn] 6d1 7s2",
    "electronegativity": 1.1,
    "ionization_energies": [
      499,
      1170
    ],
    "melt": 1500,
    "molar_heat": 27.2,
    "namer": null,
    "number": 89,
    "period": 7,
    "phase": "Solid",
    "shells": [
      2,
      8,
      18,
      32,
      18,
      9,
      2
    ],
    "group": "Actinide",
    "name": "Actinium",
    "family": 3
  },
  "Th": {
    "appearance": "silvery, often with black tarnish",
    "mass": 232.03774,
    "block": "f",
    "boil": 5061,
    "density": 11.724,
    "discoverer": "Jöns Jakob Berzelius",
    "electron_affinity": 112.72,
    "electron_configuration": "[Rn] 6d2 7s2",
    "electronegativity": 1.3,
    "ionization_energies": [
      587,
      1110,
      1930,
      2780
    ],
    "melt": 2023,
    "molar_heat": 26.23,
    "namer": null,
    "number": 90,
    "period": 7,
    "phase": "Solid",
    "shells": [
      2,
      8,
      18,
      32,
      18,
      10,
      2
    ],
    "group": "Actinide",
    "name": "Thorium",
    "family": 3
  },
  "Pa": {
    "appearance": "bright, silvery metallic luster",
    "mass": 231.035882,
    "block": "f",
    "boil": 4300,
    "density": 15.37,
    "discoverer": "William Crookes",
    "electron_affinity": 53.03,
    "electron_configuration": "[Rn] 5f2 6d1 7s2",
    "electronegativity": 1.5,
    "ionization_energies": [
      568
    ],
    "melt": 1841,
    "molar_heat": null,
    "namer": "Otto Hahn",
    "number": 91,
    "period": 7,
    "phase": "Solid",
    "shells": [
      2,
      8,
      18,
      32,
      20,
      9,
      2
    ],
    "group": "Actinide",
    "name": "Protactinium",
    "family": 3
  },
  "U": {
    "appearance": null,
    "mass": 238.028913,
    "block": "f",
    "boil": 4404,
    "density": 19.1,
    "discoverer": "Martin Heinrich Klaproth",
    "electron_affinity": 50.94,
    "electron_configuration": "[Rn] 5f3 6d1 7s2",
    "electronegativity": 1.38,
    "ionization_energies": [
      597.6,
      1420
    ],
    "melt": 1405.3,
    "molar_heat": 27.665,
    "namer": null,
    "number": 92,
    "period": 7,
    "phase": "Solid",
    "shells": [
      2,
      8,
      18,
      32,
      21,
      9,
      2
    ],
    "group": "Actinide",
    "name": "Uranium",
    "family": 3
  },
  "Np": {
    "appearance": "silvery metallic",
    "mass": 237,
    "block": "f",
    "boil": 4447,
    "density": 20.45,
    "discoverer": "Edwin McMillan",
    "electron_affinity": 45.85,
    "electron_configuration": "[Rn] 5f4 6d1 7s2",
    "electronegativity": 1.36,
    "ionization_energies": [
      604.5
    ],
    "melt": 912,
    "molar_heat": 29.46,
    "namer": null,
    "number": 93,
    "period": 7,
    "phase": "Solid",
    "shells": [
      2,
      8,
      18,
      32,
      22,
      9,
      2
    ],
    "group": "Actinide",
    "name": "Neptunium",
    "family": 3
  },
  "Pu": {
    "appearance": "silvery white, tarnishing to dark gray in air",
    "mass": 244,
    "block": "f",
    "boil": 3505,
    "density": 19.816,
    "discoverer": "Glenn T. Seaborg",
    "electron_affinity": -48.33,
    "electron_configuration": "[Rn] 5f6 7s2",
    "electronegativity": 1.28,
    "ionization_energies": [
      584.7
    ],
    "melt": 912.5,
    "molar_heat": 35.5,
    "namer": null,
    "number": 94,
    "period": 7,
    "phase": "Solid",
    "shells": [
      2,
      8,
      18,
      32,
      24,
      8,
      2
    ],
    "group": "Actinide",
    "name": "Plutonium",
    "family": 3
  },
  "Am": {
    "appearance": "silvery white",
    "mass": 243,
    "block": "f",
    "boil": 2880,
    "density": 12,
    "discoverer": "Glenn T. Seaborg",
    "electron_affinity": 9.93,
    "electron_configuration": "[Rn] 5f7 7s2",
    "electronegativity": 1.13,
    "ionization_energies": [
      578
    ],
    "melt": 1449,
    "molar_heat": 62.7,
    "namer": null,
    "number": 95,
    "period": 7,
    "phase": "Solid",
    "shells": [
      2,
      8,
      18,
      32,
      25,
      8,
      2
    ],
    "group": "Actinide",
    "name": "Americium",
    "family": 3
  },
  "Cm": {
    "appearance": "silvery metallic, glows purple in the dark",
    "mass": 247,
    "block": "f",
    "boil": 3383,
    "density": 13.51,
    "discoverer": "Glenn T. Seaborg",
    "electron_affinity": 27.17,
    "electron_configuration": "[Rn] 5f7 6d1 7s2",
    "electronegativity": 1.28,
    "ionization_energies": [
      581
    ],
    "melt": 1613,
    "molar_heat": null,
    "namer": null,
    "number": 96,
    "period": 7,
    "phase": "Solid",
    "shells": [
      2,
      8,
      18,
      32,
      25,
      9,
      2
    ],
    "group": "Actinide",
    "name": "Curium",
    "family": 3
  },
  "Bk": {
    "appearance": "silvery",
    "mass": 247,
    "block": "f",
    "boil": 2900,
    "density": 14.78,
    "discoverer": "Lawrence Berkeley National Laboratory",
    "electron_affinity": -165.24,
    "electron_configuration": "[Rn] 5f9 7s2",
    "electronegativity": 1.3,
    "ionization_energies": [
      601
    ],
    "melt": 1259,
    "molar_heat": null,
    "namer": null,
    "number": 97,
    "period": 7,
    "phase": "Solid",
    "shells": [
      2,
      8,
      18,
      32,
      27,
      8,
      2
    ],
    "group": "Actinide",
    "name": "Berkelium",
    "family": 3
  },
  "Cf": {
    "appearance": "silvery",
    "mass": 251,
    "block": "f",
    "boil": 1743,
    "density": 15.1,
    "discoverer": "Lawrence Berkeley National Laboratory",
    "electron_affinity": -97.31,
    "electron_configuration": "[Rn] 5f10 7s2",
    "electronegativity": 1.3,
    "ionization_energies": [
      608
    ],
    "melt": 1173,
    "molar_heat": null,
    "namer": null,
    "number": 98,
    "period": 7,
    "phase": "Solid",
    "shells": [
      2,
      8,
      18,
      32,
      28,
      8,
      2
    ],
    "group": "Actinide",
    "name": "Californium",
    "family": 3
  },
  "Es": {
    "appearance": "silver-colored",
    "mass": 252,
    "block": "f",
    "boil": 1269,
    "density": 8.84,
    "discoverer": "Lawrence Berkeley National Laboratory",
    "electron_affinity": -28.6,
    "electron_configuration": "[Rn] 5f11 7s2",
    "electronegativity": 1.3,
    "ionization_energies": [
      619
    ],
    "melt": 1133,
    "molar_heat": null,
    "namer": null,
    "number": 99,
    "period": 7,
    "phase": "Solid",
    "shells": [
      2,
      8,
      18,
      32,
      29,
      8,
      2
    ],
    "group": "Actinide",
    "name": "Einsteinium",
    "family": 3
  },
  "Fm": {
    "appearance": null,
    "mass": 257,
    "block": "f",
    "boil": null,
    "density": null,
    "discoverer": "Lawrence Berkeley National Laboratory",
    "electron_affinity": 33.96,
    "electron_configuration": "[Rn] 5f12 7s2",
    "electronegativity": 1.3,
    "ionization_energies": [
      627
    ],
    "melt": 1800,
    "molar_heat": null,
    "namer": null,
    "number": 100,
    "period": 7,
    "phase": "Solid",
    "shells": [
      2,
      8,
      18,
      32,
      30,
      8,
      2
    ],
    "group": "Actinide",
    "name": "Fermium",
    "family": 3
  },
  "Md": {
    "appearance": null,
    "mass": 258,
    "block": "f",
    "boil": null,
    "density": null,
    "discoverer": "Lawrence Berkeley National Laboratory",
    "electron_affinity": 93.91,
    "electron_configuration": "[Rn] 5f13 7s2",
    "electronegativity": 1.3,
    "ionization_energies": [
      635
    ],
    "melt": 1100,
    "molar_heat": null,
    "namer": null,
    "number": 101,
    "period": 7,
    "phase": "Solid",
    "shells": [
      2,
      8,
      18,
      32,
      31,
      8,
      2
    ],
    "group": "Actinide",
    "name": "Mendelevium",
    "family": 3
  },
  "No": {
    "appearance": null,
    "mass": 259,
    "block": "f",
    "boil": null,
    "density": null,
    "discoverer": "Joint Institute for Nuclear Research",
    "electron_affinity": -223.22,
    "electron_configuration": "[Rn] 5f14 7s2",
    "electronegativity": 1.3,
    "ionization_energies": [
      642
    ],
    "melt": 1100,
    "molar_heat": null,
    "namer": null,
    "number": 102,
    "period": 7,
    "phase": "Solid",
    "shells": [
      2,
      8,
      18,
      32,
      32,
      8,
      2
    ],
    "group": "Actinide",
    "name": "Nobelium",
    "family": 3
  },
  "Lr": {
    "appearance": null,
    "mass": 266,
    "block": "d",
    "boil": null,
    "density": null,
    "discoverer": "Lawrence Berkeley National Laboratory",
    "electron_affinity": -30.04,
    "electron_configuration": "[Rn] 5f14 7s2 7p1",
    "electronegativity": 1.3,
    "ionization_energies": [
      470
    ],
    "melt": 1900,
    "molar_heat": null,
    "namer": null,
    "number": 103,
    "period": 7,
    "phase": "Solid",
    "shells": [
      2,
      8,
      18,
      32,
      32,
      8,
      3
    ],
    "group": "Actinide",
    "name": "Lawrencium",
    "family": 3
  },
  "Rf": {
    "appearance": null,
    "mass": 267,
    "block": "d",
    "boil": 5800,
    "density": 23.2,
    "discoverer": "Joint Institute for Nuclear Research",
    "electron_affinity": null,
    "electron_configuration": "[Rn] 5f14 6d2 7s2",
    "electronegativity": null,
    "ionization_energies": [
      580
    ],
    "melt": 2400,
    "molar_heat": null,
    "namer": null,
    "number": 104,
    "period": 7,
    "phase": "Solid",
    "shells": [
      2,
      8,
      18,
      32,
      32,
      10,
      2
    ],
    "group": "Transition Metal",
    "name": "Rutherfordium",
    "family": 4
  },
  "Db": {
    "appearance": null,
    "mass": 268,
    "block": "d",
    "boil": null,
    "density": 29.3,
    "discoverer": "Joint Institute for Nuclear Research",
    "electron_affinity": null,
    "electron_configuration": "[Rn] 5f14 6d3 7s2",
    "electronegativity": null,
    "ionization_energies": [],
    "melt": null,
    "molar_heat": null,
    "namer": null,
    "number": 105,
    "period": 7,
    "phase": "Solid",
    "shells": [
      2,
      8,
      18,
      32,
      32,
      11,
      2
    ],
    "group": "Transition Metal",
    "name": "Dubnium",
    "family": 5
  },
  "Sg": {
    "appearance": null,
    "mass": 269,
    "block": "d",
    "boil": null,
    "density": 35,
    "discoverer": "Lawrence Berkeley National Laboratory",
    "electron_affinity": null,
    "electron_configuration": "[Rn] 5f14 6d4 7s2",
    "electronegativity": null,
    "ionization_energies": [],
    "melt": null,
    "molar_heat": null,
    "namer": null,
    "number": 106,
    "period": 7,
    "phase": "Solid",
    "shells": [
      2,
      8,
      18,
      32,
      32,
      12,
      2
    ],
    "group": "Transition Metal",
    "name": "Seaborgium",
    "family": 6
  },
  "Bh": {
    "appearance": null,
    "mass": 270,
    "block": "d",
    "boil": null,
    "density": 37.1,
    "discoverer": "Gesellschaft für Schwerionenforschung",
    "electron_affinity": null,
    "electron_configuration": "[Rn] 5f14 6d5 7s2",
    "electronegativity": null,
    "ionization_energies": [],
    "melt": null,
    "molar_heat": null,
    "namer": null,
    "number": 107,
    "period": 7,
    "phase": "Solid",
    "shells": [
      2,
      8,
      18,
      32,
      32,
      13,
      2
    ],
    "group": "Transition Metal",
    "name": "Bohrium",
    "family": 7
  },
  "Hs": {
    "appearance": null,
    "mass": 269,
    "block": "d",
    "boil": null,
    "density": 40.7,
    "discoverer": "Gesellschaft für Schwerionenforschung",
    "electron_affinity": null,
    "electron_configuration": "[Rn] 5f14 6d6 7s2",
    "electronegativity": null,
    "ionization_energies": [],
    "melt": 126,
    "molar_heat": null,
    "namer": null,
    "number": 108,
    "period": 7,
    "phase": "Solid",
    "shells": [
      2,
      8,
      18,
      32,
      32,
      14,
      2
    ],
    "group": "Transition Metal",
    "name": "Hassium",
    "family": 8
  },
  "Mt": {
    "appearance": null,
    "mass": 278,
    "block": "d",
    "boil": null,
    "density": 37.4,
    "discoverer": "Gesellschaft für Schwerionenforschung",
    "electron_affinity": null,
    "electron_configuration": "[Rn] 5f14 6d7 7s2",
    "electronegativity": null,
    "ionization_energies": [],
    "melt": null,
    "molar_heat": null,
    "namer": null,
    "number": 109,
    "period": 7,
    "phase": "Solid",
    "shells": [
      2,
      8,
      18,
      32,
      32,
      15,
      2
    ],
    "group": "Unknown",
    "name": "Meitnerium",
    "family": 9
  },
  "Ds": {
    "appearance": null,
    "mass": 281,
    "block": "d",
    "boil": null,
    "density": 34.8,
    "discoverer": "Gesellschaft für Schwerionenforschung",
    "electron_affinity": null,
    "electron_configuration": "[Rn] 5f14 6d9 7s1",
    "electronegativity": null,
    "ionization_energies": [],
    "melt": null,
    "molar_heat": null,
    "namer": null,
    "number": 110,
    "period": 7,
    "phase": "Solid",
    "shells": [
      2,
      8,
      18,
      32,
      32,
      16,
      2
    ],
    "group": "Unknown",
    "name": "Darmstadtium",
    "family": 10
  },
  "Rg": {
    "appearance": null,
    "mass": 282,
    "block": "d",
    "boil": null,
    "density": 28.7,
    "discoverer": "Gesellschaft für Schwerionenforschung",
    "electron_affinity": 151,
    "electron_configuration": "[Rn] 5f14 6d10 7s1",
    "electronegativity": null,
    "ionization_energies": [],
    "melt": null,
    "molar_heat": null,
    "namer": null,
    "number": 111,
    "period": 7,
    "phase": "Solid",
    "shells": [
      2,
      8,
      18,
      32,
      32,
      17,
      2
    ],
    "group": "Unknown",
    "name": "Roentgenium",
    "family": 11
  },
  "Cn": {
    "appearance": null,
    "mass": 285,
    "block": "d",
    "boil": 3570,
    "density": 14,
    "discoverer": "Gesellschaft für Schwerionenforschung",
    "electron_affinity": null,
    "electron_configuration": "[Rn] 5f14 6d10 7s2",
    "electronegativity": null,
    "ionization_energies": [],
    "melt": null,
    "molar_heat": null,
    "namer": null,
    "number": 112,
    "period": 7,
    "phase": "Liquid",
    "shells": [
      2,
      8,
      18,
      32,
      32,
      18,
      2
    ],
    "group": "Transition Metal",
    "name": "Copernicium",
    "family": 12
  },
  "Nh": {
    "appearance": null,
    "mass": 286,
    "block": "p",
    "boil": 1430,
    "density": 16,
    "discoverer": "RIKEN",
    "electron_affinity": 66.6,
    "electron_configuration": "[Rn] 5f14 6d10 7s2 7p1",
    "electronegativity": null,
    "ionization_energies": [],
    "melt": 700,
    "molar_heat": null,
    "namer": null,
    "number": 113,
    "period": 7,
    "phase": "Solid",
    "shells": [
      2,
      8,
      18,
      32,
      32,
      18,
      3
    ],
    "group": "Unknown",
    "name": "Nihonium",
    "family": 13
  },
  "Fl": {
    "appearance": null,
    "mass": 289,
    "block": "p",
    "boil": 420,
    "density": 14,
    "discoverer": "Joint Institute for Nuclear Research",
    "electron_affinity": null,
    "electron_configuration": "[Rn] 5f14 6d10 7s2 7p2",
    "electronegativity": null,
    "ionization_energies": [],
    "melt": 340,
    "molar_heat": null,
    "namer": null,
    "number": 114,
    "period": 7,
    "phase": "Solid",
    "shells": [
      2,
      8,
      18,
      32,
      32,
      18,
      4
    ],
    "group": "Post-Transition Metal",
    "name": "Flerovium",
    "family": 14
  },
  "Mc": {
    "appearance": null,
    "mass": 289,
    "block": "p",
    "boil": 1400,
    "density": 13.5,
    "discoverer": "Joint Institute for Nuclear Research",
    "electron_affinity": 35.3,
    "electron_configuration": "[Rn] 5f14 6d10 7s2 7p3",
    "electronegativity": null,
    "ionization_energies": [],
    "melt": 670,
    "molar_heat": null,
    "namer": null,
    "number": 115,
    "period": 7,
    "phase": "Solid",
    "shells": [
      2,
      8,
      18,
      32,
      32,
      18,
      5
    ],
    "group": "Unknown",
    "name": "Moscovium",
    "family": 15
  },
  "Lv": {
    "appearance": null,
    "mass": 293,
    "block": "p",
    "boil": 1085,
    "density": 12.9,
    "discoverer": "Joint Institute for Nuclear Research",
    "electron_affinity": 74.9,
    "electron_configuration": "[Rn] 5f14 6d10 7s2 7p4",
    "electronegativity": null,
    "ionization_energies": [],
    "melt": 709,
    "molar_heat": null,
    "namer": null,
    "number": 116,
    "period": 7,
    "phase": "Solid",
    "shells": [
      2,
      8,
      18,
      32,
      32,
      18,
      6
    ],
    "group": "Unknown",
    "name": "Livermorium",
    "family": 16
  },
  "Ts": {
    "appearance": null,
    "mass": 294,
    "block": "p",
    "boil": 883,
    "density": 7.17,
    "discoverer": "Joint Institute for Nuclear Research",
    "electron_affinity": 165.9,
    "electron_configuration": "[Rn] 5f14 6d10 7s2 7p5",
    "electronegativity": null,
    "ionization_energies": [],
    "melt": 723,
    "molar_heat": null,
    "namer": null,
    "number": 117,
    "period": 7,
    "phase": "Solid",
    "shells": [
      2,
      8,
      18,
      32,
      32,
      18,
      7
    ],
    "group": "Unknown",
    "name": "Tennessine",
    "family": 17
  },
  "Og": {
    "appearance": null,
    "mass": 294,
    "block": "p",
    "boil": 350,
    "density": 4.95,
    "discoverer": "Joint Institute for Nuclear Research",
    "electron_affinity": 5.40318,
    "electron_configuration": "[Rn] 5f14 6d10 7s2 7p6",
    "electronegativity": null,
    "ionization_energies": [],
    "melt": null,
    "molar_heat": null,
    "namer": null,
    "number": 118,
    "period": 7,
    "phase": "Solid",
    "shells": [
      2,
      8,
      18,
      32,
      32,
      18,
      8
    ],
    "group": "Unknown",
    "name": "Oganesson",
    "family": 18
  },
  "Uue": {
    "appearance": null,
    "mass": 315,
    "block": "s",
    "boil": 630,
    "density": 3,
    "discoverer": "GSI Helmholtz Centre for Heavy Ion Research",
    "electron_affinity": 63.87,
    "electron_configuration": "[Og] 8s1",
    "electronegativity": null,
    "ionization_energies": [],
    "melt": null,
    "molar_heat": null,
    "namer": null,
    "number": 119,
    "period": 8,
    "phase": "Solid",
    "shells": [
      2,
      8,
      18,
      32,
      32,
      18,
      8,
      1
    ],
    "group": "Unknown",
    "name": "Ununennium",
    "family": 1
  }
}